{"rabbit_version":"3.9.12","rabbitmq_version":"3.9.12","product_name":"RabbitMQ","product_version":"3.9.12","users":[{"name":"rabbittest","password_hash":"DnkagwCXFYkP7zrj7Ly+i1oxfkFdxW8jwYMLfJ9a3lEY9sVr","hashing_algorithm":"rabbit_password_hashing_sha256","tags":["administrator"],"limits":{}}],"vhosts":[{"name":"/"}],"permissions":[{"user":"rabbittest","vhost":"/","configure":".*","write":".*","read":".*"}],"topic_permissions":[{"user":"rabbittest","vhost":"/","exchange":"","write":".*","read":".*"}],"parameters":[],"global_parameters":[{"name":"internal_cluster_id","value":"rabbitmq-cluster-id-VaxNRKupldZiBh5KVKxvXg"}],"policies":[],"queues":[],"exchanges":[],"bindings":[]}
